ml_supertrend_mt5/__init__.py
ml_supertrend_mt5/backtest_engine.py
ml_supertrend_mt5/config.json
ml_supertrend_mt5/examples.py
ml_supertrend_mt5/run_bot.py
ml_supertrend_mt5/core/__init__.py
ml_supertrend_mt5/core/news_filter.py
ml_supertrend_mt5/core/performance_monitor.py
ml_supertrend_mt5/core/risk_manager.py
ml_supertrend_mt5/core/supertrend_bot.py
ml_supertrend_mt5/tests/__init__.py
ml_supertrend_mt5-1.0.0.dist-info/licenses/LICENSE
ml_supertrend_mt5-1.0.0.dist-info/METADATA
ml_supertrend_mt5-1.0.0.dist-info/WHEEL
ml_supertrend_mt5-1.0.0.dist-info/entry_points.txt
ml_supertrend_mt5-1.0.0.dist-info/top_level.txt
ml_supertrend_mt5-1.0.0.dist-info/RECORD
