Metadata-Version: 2.4
Name: ml-supertrend-mt5
Version: 1.0.0
Summary: Advanced SuperTrend trading bot for MetaTrader 5 with Machine Learning clustering
Home-page: https://github.com/xPOURY4/ML-SuperTrend-MT5
Author: xPOURY4
Author-email: 
License: MIT
Project-URL: Homepage, https://github.com/xPOURY4/ML-SuperTrend-MT5
Project-URL: Bug Tracker, https://github.com/xPOURY4/ML-SuperTrend-MT5/issues
Project-URL: Documentation, https://github.com/xPOURY4/ML-SuperTrend-MT5#readme
Project-URL: Source Code, https://github.com/xPOURY4/ML-SuperTrend-MT5
Project-URL: Twitter, https://twitter.com/TheRealPourya
Keywords: trading,forex,metatrader5,mt5,supertrend,machine-learning,algorithmic-trading
Classifier: Development Status :: 4 - Beta
Classifier: Intended Audience :: Financial and Insurance Industry
Classifier: Topic :: Office/Business :: Financial :: Investment
Classifier: License :: OSI Approved :: MIT License
Classifier: Programming Language :: Python :: 3
Classifier: Programming Language :: Python :: 3.8
Classifier: Programming Language :: Python :: 3.9
Classifier: Programming Language :: Python :: 3.10
Classifier: Programming Language :: Python :: 3.11
Classifier: Operating System :: Microsoft :: Windows
Requires-Python: >=3.8
License-File: LICENSE
Requires-Dist: MetaTrader5>=5.0.45
Requires-Dist: pandas>=1.3.0
Requires-Dist: numpy>=1.21.0
Requires-Dist: scikit-learn>=1.0.0
Requires-Dist: matplotlib>=3.4.0
Requires-Dist: seaborn>=0.11.0
Requires-Dist: TA-Lib>=0.4.24
Requires-Dist: requests>=2.25.0
Requires-Dist: python-dateutil>=2.8.0
Requires-Dist: pytz>=2021.1
Requires-Dist: colorama>=0.4.4
Requires-Dist: tqdm>=4.61.0
Dynamic: home-page
Dynamic: license-file
Dynamic: requires-python
